ecovacs_robot_mcp.py
ecovacs_robot_mcp-0.1.9.dist-info/licenses/LICENSE
ecovacs_robot_mcp-0.1.9.dist-info/METADATA
ecovacs_robot_mcp-0.1.9.dist-info/WHEEL
ecovacs_robot_mcp-0.1.9.dist-info/top_level.txt
ecovacs_robot_mcp-0.1.9.dist-info/RECORD
